[
    {
        "page": 1,
        "raw_text": "NORMALIZACIÓN\nActa:24797839\nCliente:384391 OBANDO MOGOLLON HECTOR JOSE\nDirección:CRA 7 8 BARRIO SAN ANTONIO - SAN ANTONIO\nCapitanejo - Santander\nSeñor usuario:usted  tiene  derecho  a  ser  asistido  por  un \nelectricista con matricula profesional vigente, para  lo  cual \ntiene  20  minutos  desde  la  hora de inicio de  la revisión. \n¿Desea esta asistencia? NO\nNombre Usuario y/o Técnico: Luis Domingo Espinoza \nIdentificación y/o Matricula: 5679217\nFirma:\nInicio Revisión: 2025/02/14 09:17 a. m.\nRevisión Medidor\nMEDIDOR ENERGÍA\nRevisado\nHEXING - HXE12R\nSerie #:\n18106834\nUbicación:\nPoste\nMedida(s):\nACTIVA\nLectura\n14/feb/2025\n004486.59\nT1\nPrueba Patron\nPOT. ACTIVA POT. REACTIVA\nPOT. APARENTE\nFACTOR POT.\n% ERROR\n3.2\n0\n0\n1\n1.02\nELEMENTOS RELACIONADOS\nSello (Bornera)\nRevisado\n1038862\nESSA\nRojo TAMBOR CIERRE \nMARIPOSA \nNo existe en \nterreno \nSello (Bornera)\nInstalado\n92488352\nESSA\nCafe TAMBOR CIERRE \nMARIPOSA \nBuen Estado\nSello (Bornera)\nRetirado\n5633679\nESSA\nNegro TAMBOR CIERRE \nMARIPOSA \nBuen Estado\nSello (Caja)\nInstalado\n92488353\nESSA\nCafe TAMBOR CIERRE \nMARIPOSA \nBuen Estado\nSello (Caja)\nRetirado\n5791299\nESSA\nNegro TAMBOR CIERRE \nMARIPOSA \nBuen Estado\nSello (Coraza)\nRevisado\n90508147\nESSA\nBlanco TAMBOR CIERRE \nMARIPOSA \nBuen Estado\n90508148\nESSA\nBlanco TAMBOR CIERRE \nMARIPOSA \nBuen Estado\nSello (Acrilico de medidor)\nRevisado\n1038868\nESSA\nRojo TAMBOR CIERRE \nMARIPOSA \nNo existe en \nterreno \n\\Estimado cliente si desea estar presente durante la evaluación \ntécnica del equipo de medida, la cual se efectuará en un \nlaboratorio debidamente acreditado, debe comunicarse a la línea \nde Atención al Cliente 018000971903 dentro de los cinco días \nhábiles siguientes al retiro del medidor. \nAforo\nDESCRIPCION\nCant\nW\nHrs\nUso\nEquipo Sonido \n1\n150\n4\nResidencial\nBombillo Ahorrador \n6\n20\n4\nResidencial\nNevera \n1\n250\n12\nResidencial\nTelevisor \n1\n150\n4\nResidencial\nDiagrama de conexiones\nEvidencia\nEvidencia\nEvidencia\nEvidencia\nEvidencia\nEvidencia\nMateriales a facturar\nELEMENTO\nCANT.\nV.UNIT.\nIVA\nFIN\nTOTAL\nREVISIÓN DE \nINSTALACIONES MEDIDOR \nMONOFÁSICO URBANO \n1\nCantidad\n119,923\n0.0%\n60\n119,923\nCINTA BANDIT 5/8\" \n2\nCantidad\n3,929\n0.0%\n60\n7,858\nAMARRE PLASTICO 4.8 \nMM * 35CM NEGRO \n10\nCantidad\n186\n0.0%\n60\n1,860\nAMARRE PLASTICO 7.8 \nMM * 55CM NEGRO \n10\nCantidad\n814\n0.0%\n60\n8,140\nHEBILLA PARA CINTA \nBANDIT 5/8\" \n2\nCantidad\n1,014\n0.0%\n60\n2,028\nTOTAL\n139,809\nResumen Impuesto\nIMPUESTO\nTOTAL\nBASE IMP.\nIVA\n0.0%\n139,809\n139,809\n0\nTOTAL\n0\nFinanciación\nCuotas: 60\nFactor: 0.0207\nValor total: 139809\nEstimado Cuota Mensual: 2894\nAcepto y conozco que además de ESSA existen diferentes \nalternativas para normalizar mi instalación, de conformidad al \nartículo 1602 del Código Civil. \nFirma:\n____________________________________\nEnterado: Luis Domingo Espinoza \nIdentificación: 5679217\nDirección: CRA 7 8 BARRIO SAN ANTONIO - SAN ANTONIO\nMunicipio: Capitanejo\nFecha revisión: 14/FEB/2025 01:07 P. M.\nEn calidad de Propietario del predio, actuo la persona Luis \nDomingo Espinoza  que atendió la visita el caso se cierra con \nestado Revision Aceptada \nObservación:\nse realiza visita técnica a predio dando cumplimiento al \nproceso 60976727 y al radicado 20240320059354, encontrando \nmedidor A1 electrónico en caja polimérica ubicado en el apoyo \n7342373 con acometida concentrica 1*8+8 área más bajante a la \nvista, con protección 1*30A, se realizan pruebas con equipo AVM \nconforme, se procede a reubicar medidor en el apoyo 7515898 ya \nque usuario tiene problemas con el vecino por el motivo que \npasan las cargas pasan por encima de la vivienda vecina, se \nrealiza aforo en presencia del usuario, se deja servicio a \nconformidad del usuario, usuario autoriza el cobro de la \nrevisión en la factura de energía, funciona casa, consumo \nproyectado 150, se toma registro fotográfico y se finaliza \nproceso IC{1-3} \n.\n____________________________________\nJuan Pablo Rincon \n.\n____________________________________\nAndres Mendoza \nFecha impresión:14/FEB/2025 01:07 P. M.\nRevisó:JUAN PABLO RINCON JAIMES\nNro terminal:ENEPER14\nCorrería:62562157\n24797839\n",
        "content": {
            "acta": "24797839",
            "cliente": "384391 OBANDO MOGOLLON HECTOR JOSE",
            "direccion": "CRA 7 8 BARRIO SAN ANTONIO - SAN ANTONIO",
            "fecha_revision": "14/FEB/2025 01:07 P. M.",
            "inspector": "JUAN PABLO RINCON JAIMES",
            "municipio": "Capitanejo",
            "medidor_instalado": null,
            "medidor_retirado": null,
            "equipos_revisados": [
                {
                    "nombre": "Bombillo Ahorrador",
                    "cantidad": 6,
                    "potencia_w": 20,
                    "uso": "4"
                },
                {
                    "nombre": "Nevera",
                    "cantidad": 1,
                    "potencia_w": 250,
                    "uso": "12"
                },
                {
                    "nombre": "Televisor",
                    "cantidad": 1,
                    "potencia_w": 150,
                    "uso": "4"
                }
            ],
            "sellos": [
                {
                    "tipo": "Sello (Bornera)",
                    "estado": "Revisado",
                    "codigo": "1038862",
                    "color": "Rojo",
                    "descripcion": "TAMBOR",
                    "ubicacion": "CIERRE \nMARIPOSA \nNo existe en \nterreno \nSello"
                },
                {
                    "tipo": "Sello (Bornera)",
                    "estado": "Retirado",
                    "codigo": "5633679",
                    "color": "Negro",
                    "descripcion": "TAMBOR",
                    "ubicacion": "CIERRE \nMARIPOSA \nBuen Estado\nSello"
                },
                {
                    "tipo": "Sello (Caja)",
                    "estado": "Retirado",
                    "codigo": "5791299",
                    "color": "Negro",
                    "descripcion": "TAMBOR",
                    "ubicacion": "CIERRE \nMARIPOSA \nBuen Estado\nSello"
                },
                {
                    "tipo": "Sello (Acrilico de medidor)",
                    "estado": "Revisado",
                    "codigo": "1038868",
                    "color": "Rojo",
                    "descripcion": "TAMBOR",
                    "ubicacion": "CIERRE \nMARIPOSA \nNo existe en \nterreno"
                }
            ],
            "situacion_encontrada": null,
            "observaciones": "se realiza visita técnica a predio dando cumplimiento al \nproceso 60976727 y al radicado 20240320059354, encontrando \nmedidor A1 electrónico en caja polimérica ubicado en el apoyo \n7342373 con acometida concentrica 1*8+8 área más bajante a la \nvista, con protección 1*30A, se realizan pruebas con equipo AVM \nconforme, se procede a reubicar medidor en el apoyo 7515898 ya \nque usuario tiene problemas con el vecino por el motivo que \npasan las cargas pasan por encima de la vivienda vecina, se \nrealiza aforo en presencia del usuario, se deja servicio a \nconformidad del usuario, usuario autoriza el cobro de la \nrevisión en la factura de energía, funciona casa, consumo \nproyectado 150, se toma registro fotográfico y se finaliza \nproceso IC{1-3} \n.\n____________________________________\nJuan Pablo Rincon \n.\n____________________________________\nAndres Mendoza \nFecha impresión:14/FEB/2025 01:07 P. M.\nRevisó:JUAN PABLO RINCON JAIMES\nNro terminal:ENEPER14\nCorrería:62562157\n24797839",
            "total_materiales": 139809.0
        }
    }
]